numpack-0.5.0.dist-info/METADATA
numpack-0.5.0.dist-info/WHEEL
numpack-0.5.0.dist-info/licenses/LICENSE
numpack/__init__.py
numpack/_lib_numpack.cpython-310-darwin.so
numpack/io/__init__.py
numpack/io/csv_io.py
numpack/io/feather_io.py
numpack/io/hdf5_io.py
numpack/io/numpy_io.py
numpack/io/package_io.py
numpack/io/pandas_io.py
numpack/io/parquet_io.py
numpack/io/pytorch_io.py
numpack/io/s3_io.py
numpack/io/safetensors_io.py
numpack/io/utils.py
numpack/io/zarr_io.py
numpack/io/zero_copy.py
numpack/tests/__init__.py
numpack/tests/conftest.py
numpack/tests/test_advanced_api.py
numpack/tests/test_batch_modes.py
numpack/tests/test_cross_platform.py
numpack/tests/test_diagnose_inplace.py
numpack/tests/test_drop_append_lazy.py
numpack/tests/test_drop_scenarios.py
numpack/tests/test_inplace_operators.py
numpack/tests/test_io_conversion.py
numpack/tests/test_lazy_array_advanced.py
numpack/tests/test_lazy_array_operators.py
numpack/tests/test_numpack.py
numpack/tests/test_open_close.py
numpack/tests/test_package_io.py
numpack/tests/test_thread_safety.py
numpack/tests/test_user_intent.py
numpack/tests/test_vector_engine.py
numpack/tests/test_windows_handles.py
numpack/tests/test_zero_copy.py
numpack/vector_engine/__init__.py
numpack/writable_array.py
numpack-0.5.0.dist-info/RECORD
