Metadata-Version: 2.4
Name: numpack
Version: 0.5.0
Classifier: Development Status :: 4 - Beta
Classifier: Intended Audience :: Developers
Classifier: License :: OSI Approved :: Apache Software License
Classifier: Programming Language :: Python :: 3
Classifier: Programming Language :: Python :: 3.9
Classifier: Programming Language :: Python :: 3.10
Classifier: Programming Language :: Python :: 3.11
Classifier: Programming Language :: Python :: 3.12
Classifier: Programming Language :: Python :: 3.13
Classifier: Programming Language :: Rust
Classifier: Topic :: Software Development :: Libraries :: Python Modules
Classifier: Topic :: Scientific/Engineering :: Mathematics
Requires-Dist: numpy>=1.26.0
License-File: LICENSE
Summary: A high-performance array storage and manipulation library
Keywords: numpy,array,storage,performance
Author: NumPack Contributors
Requires-Python: >=3.9
